configme
setup.py
configme/__init__.py
configme/__main__.py
configme/configme.py
configme/filters.py
configme.egg-info/PKG-INFO
configme.egg-info/SOURCES.txt
configme.egg-info/dependency_links.txt
configme.egg-info/entry_points.txt
configme.egg-info/requires.txt
configme.egg-info/top_level.txt