Metadata-Version: 1.1
Name: configme
Version: 0.0.4
Summary: A template based config file generator for general purposes.
Home-page: https://github.com/supercoffee/configme
Author: Benjamin Daschel
Author-email: coffeemaxed@gmail.com
License: UNLICENSE
Keywords: cli
Platform: UNKNOWN
Classifier: Intended Audience :: Developers
Classifier: Programming Language :: Python :: 2.7
